c12_callisto_clients/__init__.py
c12_callisto_clients/user_configs.py
c12_callisto_clients/api/__init__.py
c12_callisto_clients/api/client.py
c12_callisto_clients/api/configs.py
c12_callisto_clients/api/exceptions.py
c12_callisto_clients/pytket/__init__.py
c12_callisto_clients/pytket/extensions/__init__.py
c12_callisto_clients/pytket/extensions/callisto/__init__.py
c12_callisto_clients/pytket/extensions/callisto/backends/__init__.py
c12_callisto_clients/pytket/extensions/callisto/backends/callisto.py
c12_callisto_clients/qiskit/__init__.py
c12_callisto_clients/qiskit/c12sim_backend.py
c12_callisto_clients/qiskit/c12sim_job.py
c12_callisto_clients/qiskit/c12sim_provider.py
c12_callisto_clients/qiskit/exceptions.py
c12_callisto_clients/qiskit_back/__init__.py
c12_callisto_clients/qiskit_back/c12sim_backend.py
c12_callisto_clients/qiskit_back/c12sim_job.py
c12_callisto_clients/qiskit_back/c12sim_provider.py
c12_callisto_clients/qiskit_back/exceptions.py
c12_callisto_clients-2.2.2.dist-info/METADATA
c12_callisto_clients-2.2.2.dist-info/WHEEL
c12_callisto_clients-2.2.2.dist-info/top_level.txt
c12_callisto_clients-2.2.2.dist-info/RECORD
