Metadata-Version: 2.4
Name: c12_callisto_clients
Version: 2.2.2
Summary: Different adapters for the access to the C12 Callisto quantum emulator.
Author-email: C12 Quantum Electronics <dev@c12qe.com>
License: Proprietary
Project-URL: Homepage, https://www.c12qe.com
Project-URL: Repository, https://github.com/c12qe/c12simulator-clients
Project-URL: Documentation, https://c12qe.github.io/c12-callisto-clients/
Project-URL: Issues, https://github.com/c12qe/c12simulator-clients/issues
Keywords: quantum,emulator,c12,callisto,clients,pytket
Classifier: License :: Other/Proprietary License
Classifier: Programming Language :: Python :: 3 :: Only
Classifier: Programming Language :: Python :: 3.10
Classifier: Programming Language :: Python :: 3.11
Classifier: Intended Audience :: Developers
Classifier: Intended Audience :: Science/Research
Classifier: Operating System :: Microsoft :: Windows
Classifier: Operating System :: MacOS
Classifier: Operating System :: POSIX :: Linux
Classifier: Environment :: Console
Classifier: Topic :: Scientific/Engineering
Requires-Python: <3.12,>=3.10
Requires-Dist: pydantic-settings>=2.10
Requires-Dist: requests>=2.32
Requires-Dist: traitlets>=5.14
Requires-Dist: pydantic>=2.9
Requires-Dist: qiskit<1.5,>=1.4
Requires-Dist: pytket<1.34,>=1.33
Provides-Extra: qiskit
Requires-Dist: qiskit<1.5,>=1.4; extra == "qiskit"
Provides-Extra: pytket
Requires-Dist: pytket<1.34,>=1.33; extra == "pytket"
Provides-Extra: all
Requires-Dist: qiskit<1.5,>=1.4; extra == "all"
Requires-Dist: pytket<1.34,>=1.33; extra == "all"
Provides-Extra: dev
Requires-Dist: pytest>=7.1.1; extra == "dev"
